neptyne_kernel/__init__.py
neptyne_kernel/api_ref.py
neptyne_kernel/bokeh_formatter.py
neptyne_kernel/cell_address.py
neptyne_kernel/cell_address_test.py
neptyne_kernel/cell_api.py
neptyne_kernel/cell_copier.py
neptyne_kernel/cell_copier_test.py
neptyne_kernel/cell_execution_graph.py
neptyne_kernel/cell_range.py
neptyne_kernel/cell_range_test.py
neptyne_kernel/code_dependencies_parser.py
neptyne_kernel/code_highlight.py
neptyne_kernel/conftest.py
neptyne_kernel/dash.py
neptyne_kernel/dash_benchmark.py
neptyne_kernel/dash_ref.py
neptyne_kernel/dash_test.py
neptyne_kernel/dash_traceback.py
neptyne_kernel/dashref_test.py
neptyne_kernel/datetime_conversions.py
neptyne_kernel/dockerfile_test.py
neptyne_kernel/download.py
neptyne_kernel/expression_compiler.py
neptyne_kernel/expression_compiler_test.py
neptyne_kernel/formula_names.py
neptyne_kernel/get_ipython_mockable.py
neptyne_kernel/google_sheets_api_test.py
neptyne_kernel/gsheets_api.py
neptyne_kernel/gsheets_api_test.py
neptyne_kernel/insert_delete_helper.py
neptyne_kernel/insert_delete_helper_test.py
neptyne_kernel/json_tools.py
neptyne_kernel/kernel.py
neptyne_kernel/kernel_init.py
neptyne_kernel/kernel_runtime.py
neptyne_kernel/kernel_runtime_test.py
neptyne_kernel/launch_ipykernel.py
neptyne_kernel/launch_ipykernel_test.py
neptyne_kernel/linter.py
neptyne_kernel/mime_handling.py
neptyne_kernel/mime_types.py
neptyne_kernel/mutex_manager.py
neptyne_kernel/neptyne_protocol.py
neptyne_kernel/neptyne_secrets.py
neptyne_kernel/ops.py
neptyne_kernel/pandas_unrolling.py
neptyne_kernel/pip.py
neptyne_kernel/primitives.py
neptyne_kernel/primitives_test.py
neptyne_kernel/proxied_apis.py
neptyne_kernel/renderers.py
neptyne_kernel/requirements-extras.in
neptyne_kernel/requirements-formulas.in
neptyne_kernel/requirements.in
neptyne_kernel/requirements.txt
neptyne_kernel/scoped.py
neptyne_kernel/session_info.py
neptyne_kernel/sheet_api.py
neptyne_kernel/sheet_context.py
neptyne_kernel/spreadsheet_datetime.py
neptyne_kernel-0.1.9.dist-info/METADATA
neptyne_kernel-0.1.9.dist-info/WHEEL
neptyne_kernel-0.1.9.dist-info/top_level.txt
neptyne_kernel-0.1.9.dist-info/RECORD
